<?xml version = '1.0' encoding = 'UTF-8'?>
<TriggerOraclev10g class="oracle.dbtools.crest.model.design.storage.oracle.v10g.TriggerOraclev10g" name="DVM_PTA_ERRORS_AUTO_BRI" directorySegmentName="seg_0" id="F104B237-A168-A084-D04D-F5B89EF824FB">
<sourceConnName>DevVM_PDB_CEN_CRUISE</sourceConnName>
<sourceObjSchema>CEN_CRUISE</sourceObjSchema>
<sourceObjName>DVM_PTA_ERRORS_AUTO_BRI</sourceObjName>
<createdBy>Jesse.Abdul</createdBy>
<createdTime>2020-05-14 01:39:50 UTC</createdTime>
<ownerDesignName>DVM</ownerDesignName>
<actions>INSERT</actions>
<body><![CDATA[begin
select DVM_PTA_ERRORS_SEQ.nextval into :new.PTA_ERROR_ID from dual;
end;
]]></body>
<triggerTime>BEFORE</triggerTime>
<owner>E8DCB2C6-61E3-B61C-EA16-BC4682DB6CE1</owner>
<table>83932E29-ABD2-45B5-A580-469F0761143A</table>
</TriggerOraclev10g>
